picotts/__init__.py
py_picotts-0.1.2.dist-info/DESCRIPTION.rst
py_picotts-0.1.2.dist-info/METADATA
py_picotts-0.1.2.dist-info/RECORD
py_picotts-0.1.2.dist-info/WHEEL
py_picotts-0.1.2.dist-info/metadata.json
py_picotts-0.1.2.dist-info/top_level.txt
