Metadata-Version: 2.0
Name: py-picotts
Version: 0.1.2
Summary: Python interface for SVOX Pico TTS pico2wave
Home-page: https://github.com/gooofy/py-picotts
Author: Guenter Bartsch
Author-email: guenter@zamia.org
License: Apache
Platform: Linux
Classifier: Topic :: Multimedia :: Sound/Audio :: Sound Synthesis
Classifier: Topic :: Multimedia :: Sound/Audio :: Speech
Classifier: Operating System :: POSIX :: Linux
Classifier: License :: OSI Approved :: Apache Software License
Classifier: Programming Language :: Python :: 2
Classifier: Programming Language :: Python :: 2.7
Classifier: Programming Language :: Python :: 3
Classifier: Programming Language :: Python :: 3.4
